aba_cli_scrapper/.env
aba_cli_scrapper/__init__.py
aba_cli_scrapper/__main__.py
aba_cli_scrapper/ascii.py
aba_cli_scrapper/commands.py
aba_cli_scrapper/engine_and_database.py
aba_cli_scrapper/html_to_disk.py
aba_cli_scrapper/info_message.py
aba_cli_scrapper/models.py
aba_cli_scrapper/pays_data.json
aba_cli_scrapper/proxies_providers.py
aba_cli_scrapper/proxies_utils.py
aba_cli_scrapper/scrape_from_disk.py
aba_cli_scrapper/typed_datas.py
aba_cli_scrapper/utils_scrapping.py
images/__init__.py
images/aba-run-help-image.png
images/ai-agent-help.png
images/db-init-help-options.png
images/db-init-options.png
images/db-update-help.png
images/export-as-csv-demo.gif
images/export-as-csv-help.png
images/help-cli-2.png
images/image.png
images/inroduce_scraper.jpg
images/short-demo.mp4
images/syphoon-scraper-help-options.png
images/syphoon-scraper-subcommand-options.png
pyproject.toml
aba_cli_scrapper-0.7.6.dist-info/LICENSE.txt
aba_cli_scrapper-0.7.6.dist-info/METADATA
aba_cli_scrapper-0.7.6.dist-info/WHEEL
aba_cli_scrapper-0.7.6.dist-info/entry_points.txt
aba_cli_scrapper-0.7.6.dist-info/RECORD
