Metadata-Version: 2.1
Name: aba-cli-scrapper
Version: 0.7.6
Summary: Create your own Alibaba dataset and interact with it in plain English. 
Home-page: https://aba-cli-scrapper.readthedocs.io/en/latest/
License: GNU GENERAL PUBLIC LICENSEVersion 3, 29 June 2007
Keywords: cli,scrapping,alibaba,scraper,alibaba-cli-scrapper,dataset,ai-agent,RAG
Author: poneoneo
Author-email: onealzero@gmail.com
Requires-Python: >=3.11.0,<4.0.0
Classifier: Development Status :: 1 - Planning
Classifier: Environment :: Console
Classifier: Framework :: AsyncIO
Classifier: Intended Audience :: Developers
Classifier: Intended Audience :: Science/Research
Classifier: License :: OSI Approved :: GNU Lesser General Public License v3 (LGPLv3)
Classifier: License :: Other/Proprietary License
Classifier: Natural Language :: English
Classifier: Operating System :: Microsoft :: Windows :: Windows 10
Classifier: Programming Language :: Python :: 3
Classifier: Programming Language :: Python :: 3.11
Classifier: Programming Language :: Python :: 3.12
Classifier: Topic :: Scientific/Engineering :: Information Analysis
Classifier: Topic :: Terminals
Classifier: Typing :: Typed
Requires-Dist: aiosignal (==1.3.1) ; python_version >= "3.7"
Requires-Dist: annotated-types (==0.7.0) ; python_version >= "3.8"
Requires-Dist: attrs (==23.2.0) ; python_version >= "3.7"
Requires-Dist: certifi (==2024.7.4) ; python_version >= "3.6"
Requires-Dist: cffi (==1.16.0) ; platform_python_implementation != "PyPy"
Requires-Dist: charset-normalizer (==3.3.2) ; python_full_version >= "3.7.0"
Requires-Dist: click (==8.1.7) ; python_version >= "3.7"
Requires-Dist: colorama (==0.4.6) ; sys_platform == "win32"
Requires-Dist: cryptography (==43.0.1) ; python_version >= "3.7"
Requires-Dist: datahorse (>=0.0.3,<0.0.4)
Requires-Dist: frozenlist (==1.4.1) ; python_version >= "3.8"
Requires-Dist: furo (>=2024.8.6,<2025.0.0)
Requires-Dist: greenlet (==3.0.3) ; python_version >= "3.7"
Requires-Dist: idna (==3.7) ; python_version >= "3.5"
Requires-Dist: loguru (>=0.7.2,<0.8.0)
Requires-Dist: markdown-it-py (==3.0.0) ; python_version >= "3.8"
Requires-Dist: mdurl (==0.1.2) ; python_version >= "3.7"
Requires-Dist: multidict (==6.0.5) ; python_version >= "3.7"
Requires-Dist: mypy-extensions (==1.0.0) ; python_version >= "3.5"
Requires-Dist: nodeenv (==1.9.1) ; python_version >= "2.7" and python_version not in "3.0, 3.1, 3.2, 3.3, 3.4, 3.5, 3.6"
Requires-Dist: packaging (==24.1) ; python_version >= "3.8"
Requires-Dist: pandas (>=2.2.2,<3.0.0)
Requires-Dist: pathspec (==0.12.1) ; python_version >= "3.8"
Requires-Dist: platformdirs (==4.2.2) ; python_version >= "3.8"
Requires-Dist: playwright (==1.45.0)
Requires-Dist: plotnine (>=0.13.6,<0.14.0)
Requires-Dist: prettytable (>=3.11.0,<4.0.0)
Requires-Dist: pycparser (==2.22) ; python_version >= "3.8"
Requires-Dist: pydantic (==2.8.2) ; python_version >= "3.8"
Requires-Dist: pydantic-core (==2.20.1) ; python_version >= "3.8"
Requires-Dist: pyee (==11.1.0) ; python_version >= "3.8"
Requires-Dist: pygments (==2.18.0) ; python_version >= "3.8"
Requires-Dist: pymysql (>=1.1.1,<2.0.0)
Requires-Dist: python-dotenv (>=1.0.1,<2.0.0)
Requires-Dist: requests (==2.32.3) ; python_version >= "3.8"
Requires-Dist: rich (==13.7.1) ; python_full_version >= "3.7.0"
Requires-Dist: selectolax (>=0.3.21,<0.4.0)
Requires-Dist: shellingham (==1.5.4) ; python_version >= "3.7"
Requires-Dist: sqlalchemy (>=2.0.32,<3.0.0)
Requires-Dist: sqlmodel (>=0.0.21,<0.0.22)
Requires-Dist: tabulate (>=0.9.0,<0.10.0)
Requires-Dist: trogon (>=0.5.0,<0.6.0)
Requires-Dist: typer (>=0.12.5,<0.13.0)
Requires-Dist: typing-extensions (==4.12.2) ; python_version >= "3.8"
Requires-Dist: urllib3 (==2.2.2) ; python_version >= "3.8"
Requires-Dist: win32-setctime (==1.1.0) ; sys_platform == "win32"
Requires-Dist: yarl (==1.9.4) ; python_version >= "3.7"
Project-URL: Repository, https://github.com/poneoneo/Alibaba-CLI-Scraper
